ssrjson/__init__.py
ssrjson/__init__.pyi
ssrjson/py.typed
ssrjson/ssrjson.cpython-311-aarch64-linux-gnu.so
ssrjson-0.0.10.dist-info/METADATA
ssrjson-0.0.10.dist-info/WHEEL
ssrjson-0.0.10.dist-info/top_level.txt
ssrjson-0.0.10.dist-info/RECORD
ssrjson-0.0.10.dist-info/licenses/LICENSE
ssrjson-0.0.10.dist-info/licenses/LICENSE.orjson-APACHE
ssrjson-0.0.10.dist-info/licenses/LICENSE.orjson.MIT
ssrjson-0.0.10.dist-info/licenses/LICENSE.yyjson
