Metadata-Version: 2.4
Name: ssrjson
Version: 0.0.10
Summary: A high-performance Python JSON library that fully leverages modern processor capabilities.
Author-email: Antares <antares0982@gmail.com>
Classifier: Development Status :: 4 - Beta
Classifier: Programming Language :: Python :: 3
Classifier: Programming Language :: Python :: 3 :: Only
Classifier: Programming Language :: Python :: 3.10
Classifier: Programming Language :: Python :: 3.11
Classifier: Programming Language :: Python :: 3.12
Classifier: Programming Language :: Python :: 3.13
Classifier: Programming Language :: Python :: 3.14
Classifier: Programming Language :: Python :: 3.15
Classifier: Programming Language :: Python :: Implementation :: CPython
Classifier: Programming Language :: C
Classifier: Programming Language :: C++
Classifier: Operating System :: OS Independent
Classifier: License :: OSI Approved :: Apache Software License
Classifier: License :: OSI Approved :: MIT License
Requires-Python: >=3.10
License-File: LICENSE
License-File: LICENSE.orjson-APACHE
License-File: LICENSE.orjson.MIT
License-File: LICENSE.yyjson
Dynamic: license-file
